[
  {
    "tag": "Cloud 9 - https://c9.io/",
    "descr": "Cloud IDE",
    "Languages": {
      "plain": "- Java\n- Bash\n- XML\n- Python\n- Ruby\n",
      "childs": {
        "0": [
          [
            {
              "content": "Java",
              "plain": "Java\n",
              "plainChilds": "",
              "childs": []
            },
            {
              "content": "Bash",
              "plain": "Bash\n",
              "plainChilds": "",
              "childs": []
            },
            {
              "content": "XML",
              "plain": "XML\n",
              "plainChilds": "",
              "childs": []
            },
            {
              "content": "Python",
              "plain": "Python\n",
              "plainChilds": "",
              "childs": []
            },
            {
              "content": "Ruby",
              "plain": "Ruby\n",
              "plainChilds": "",
              "childs": []
            }
          ]
        ]
      }
    },
    "Extensible": {
      "plain": "- Yes\n- API\n",
      "childs": {
        "0": [
          [
            {
              "content": "Yes",
              "plain": "Yes\n",
              "plainChilds": "",
              "childs": []
            },
            {
              "content": "API",
              "plain": "API\n",
              "plainChilds": "",
              "childs": []
            }
          ]
        ]
      }
    },
    "Description": {
      "plain": "Powerful online code editor with a full Ubuntu workspace in the cloud",
      "childs": {
        "0": [
          "Powerful online code editor with a full Ubuntu workspace in the cloud"
        ]
      }
    },
    "GitSupport": {
      "plain": "- Yes\u0000",
      "childs": {
        "0": [
          [
            {
              "content": "Yes",
              "plain": "Yes\u0000",
              "plainChilds": "",
              "childs": []
            }
          ]
        ]
      }
    }
  },
  {
    "tag": "Codeanywhere - https://codeanywhere.com/",
    "descr": "Cloud IDE",
    "Languages": {
      "plain": "- Java\n- Bash\n- XML\n- Ruby\n- Python\n",
      "childs": {
        "0": [
          [
            {
              "content": "Java",
              "plain": "Java\n",
              "plainChilds": "",
              "childs": []
            },
            {
              "content": "Bash",
              "plain": "Bash\n",
              "plainChilds": "",
              "childs": []
            },
            {
              "content": "XML",
              "plain": "XML\n",
              "plainChilds": "",
              "childs": []
            },
            {
              "content": "Ruby",
              "plain": "Ruby\n",
              "plainChilds": "",
              "childs": []
            },
            {
              "content": "Python",
              "plain": "Python\n",
              "plainChilds": "",
              "childs": []
            }
          ]
        ]
      }
    },
    "Extensible": {
      "plain": "- No\n- Other\n    - Codeanywhere provides plugins/extensions that can be bought\n",
      "childs": {
        "0": [
          [
            {
              "content": "No",
              "plain": "No\n",
              "plainChilds": "",
              "childs": []
            },
            {
              "content": "Other",
              "plain": "Other\n",
              "plainChilds": "    - Codeanywhere provides plugins/extensions that can be bought\n",
              "childs": [
                {
                  "content": "Codeanywhere provides plugins/extensions that can be bought",
                  "plain": "Codeanywhere provides plugins/extensions that can be bought\n",
                  "plainChilds": "",
                  "childs": []
                }
              ]
            }
          ]
        ]
      }
    },
    "Description": {
      "plain": "Cloud IDE which supports over 72 languages, private workspaces, SSH access and many more features. ",
      "childs": {
        "0": [
          "Cloud IDE which supports over 72 languages, private workspaces, SSH access and many more features. "
        ]
      }
    },
    "GitSupport": {
      "plain": "- Yes\u0000",
      "childs": {
        "0": [
          [
            {
              "content": "Yes",
              "plain": "Yes\u0000",
              "plainChilds": "",
              "childs": []
            }
          ]
        ]
      }
    }
  },
  {
    "tag": "Codiad - http://codiad.com",
    "descr": "Web-based IDE framework",
    "Languages": {
      "plain": "- Java\n- Bash\n- XML\n- Ruby\n- Python\n",
      "childs": {
        "0": [
          [
            {
              "content": "Java",
              "plain": "Java\n",
              "plainChilds": "",
              "childs": []
            },
            {
              "content": "Bash",
              "plain": "Bash\n",
              "plainChilds": "",
              "childs": []
            },
            {
              "content": "XML",
              "plain": "XML\n",
              "plainChilds": "",
              "childs": []
            },
            {
              "content": "Ruby",
              "plain": "Ruby\n",
              "plainChilds": "",
              "childs": []
            },
            {
              "content": "Python",
              "plain": "Python\n",
              "plainChilds": "",
              "childs": []
            }
          ]
        ]
      }
    },
    "GitSupport": {
      "plain": "- Yes\n",
      "childs": {
        "0": [
          [
            {
              "content": "Yes",
              "plain": "Yes\n",
              "plainChilds": "",
              "childs": []
            }
          ]
        ]
      }
    },
    "Extensible": {
      "plain": "- Yes\n- Plugins\n",
      "childs": {
        "0": [
          [
            {
              "content": "Yes",
              "plain": "Yes\n",
              "plainChilds": "",
              "childs": []
            },
            {
              "content": "Plugins",
              "plain": "Plugins\n",
              "plainChilds": "",
              "childs": []
            }
          ]
        ]
      }
    },
    "Description": {
      "plain": "Web-based IDE framework",
      "childs": {
        "0": [
          "Web-based IDE framework"
        ]
      }
    }
  },
  {
    "tag": "Eclipse Che - https://www.eclipse.org/che/",
    "descr": "Extensible Cloud or self-hosted IDE",
    "Languages": {
      "plain": "- Java\n- Bash\n- XML\n- Python\n- Ruby\n",
      "childs": {
        "0": [
          [
            {
              "content": "Java",
              "plain": "Java\n",
              "plainChilds": "",
              "childs": []
            },
            {
              "content": "Bash",
              "plain": "Bash\n",
              "plainChilds": "",
              "childs": []
            },
            {
              "content": "XML",
              "plain": "XML\n",
              "plainChilds": "",
              "childs": []
            },
            {
              "content": "Python",
              "plain": "Python\n",
              "plainChilds": "",
              "childs": []
            },
            {
              "content": "Ruby",
              "plain": "Ruby\n",
              "plainChilds": "",
              "childs": []
            }
          ]
        ]
      }
    },
    "Extensible": {
      "plain": "- Yes\n- API\n- Plugins\n",
      "childs": {
        "0": [
          [
            {
              "content": "Yes",
              "plain": "Yes\n",
              "plainChilds": "",
              "childs": []
            },
            {
              "content": "API",
              "plain": "API\n",
              "plainChilds": "",
              "childs": []
            },
            {
              "content": "Plugins",
              "plain": "Plugins\n",
              "plainChilds": "",
              "childs": []
            }
          ]
        ]
      }
    },
    "Description": {
      "plain": "Extensible developer workspace server and cloud IDE.",
      "childs": {
        "0": [
          "Extensible developer workspace server and cloud IDE."
        ]
      }
    },
    "GitSupport": {
      "plain": "- Yes\n",
      "childs": {
        "0": [
          [
            {
              "content": "Yes",
              "plain": "Yes\n",
              "plainChilds": "",
              "childs": []
            }
          ]
        ]
      }
    }
  },
  {
    "tag": "Eclipse Orion - https://orionhub.org",
    "descr": "Cloud development environment",
    "Languages": {
      "plain": "- Java\n- Bash\n- XML\n",
      "childs": {
        "0": [
          [
            {
              "content": "Java",
              "plain": "Java\n",
              "plainChilds": "",
              "childs": []
            },
            {
              "content": "Bash",
              "plain": "Bash\n",
              "plainChilds": "",
              "childs": []
            },
            {
              "content": "XML",
              "plain": "XML\n",
              "plainChilds": "",
              "childs": []
            }
          ]
        ]
      }
    },
    "Extensible": {
      "plain": "- Yes\n- API\n- Plugins\n",
      "childs": {
        "0": [
          [
            {
              "content": "Yes",
              "plain": "Yes\n",
              "plainChilds": "",
              "childs": []
            },
            {
              "content": "API",
              "plain": "API\n",
              "plainChilds": "",
              "childs": []
            },
            {
              "content": "Plugins",
              "plain": "Plugins\n",
              "plainChilds": "",
              "childs": []
            }
          ]
        ]
      }
    },
    "Description": {
      "plain": "A modern, open source software development environment that runs in the cloud.",
      "childs": {
        "0": [
          "A modern, open source software development environment that runs in the cloud."
        ]
      }
    },
    "GitSupport": {
      "plain": "- Yes\u0000",
      "childs": {
        "0": [
          [
            {
              "content": "Yes",
              "plain": "Yes\u0000",
              "plainChilds": "",
              "childs": []
            }
          ]
        ]
      }
    }
  },
  {
    "tag": "Theia (0.0.1 alpha) - http://codiad.com",
    "descr": "Web-based IDE framework",
    "Languages": {
      "plain": "- Java\n- Python\n",
      "childs": {
        "0": [
          [
            {
              "content": "Java",
              "plain": "Java\n",
              "plainChilds": "",
              "childs": []
            },
            {
              "content": "Python",
              "plain": "Python\n",
              "plainChilds": "",
              "childs": []
            }
          ]
        ]
      }
    },
    "GitSupport": {
      "plain": "- Yes\n",
      "childs": {
        "0": [
          [
            {
              "content": "Yes",
              "plain": "Yes\n",
              "plainChilds": "",
              "childs": []
            }
          ]
        ]
      }
    },
    "Extensible": {
      "plain": "- Yes\n- Plugins\n",
      "childs": {
        "0": [
          [
            {
              "content": "Yes",
              "plain": "Yes\n",
              "plainChilds": "",
              "childs": []
            },
            {
              "content": "Plugins",
              "plain": "Plugins\n",
              "plainChilds": "",
              "childs": []
            }
          ]
        ]
      }
    },
    "Description": {
      "plain": "Still a alpha version with not much known about it. ",
      "childs": {
        "0": [
          "Still a alpha version with not much known about it. "
        ]
      }
    }
  },
  {
    "tag": "Template - http://www.example.com",
    "descr": "Default short description (with bibkey: [@esper-reference])",
    "Performance": {
      "plain": "- slow\n- fast\n",
      "childs": {
        "0": [
          [
            {
              "content": "slow",
              "plain": "slow\n",
              "plainChilds": "",
              "childs": []
            },
            {
              "content": "fast",
              "plain": "fast\n",
              "plainChilds": "",
              "childs": []
            }
          ]
        ]
      }
    },
    "License": {
      "plain": "- MIT\n- Apache 2.0\n- MPL 2.0\n",
      "childs": {
        "0": [
          [
            {
              "content": "MIT",
              "plain": "MIT\n",
              "plainChilds": "",
              "childs": []
            },
            {
              "content": "Apache 2.0",
              "plain": "Apache 2.0\n",
              "plainChilds": "",
              "childs": []
            },
            {
              "content": "MPL 2.0",
              "plain": "MPL 2.0\n",
              "plainChilds": "",
              "childs": []
            }
          ]
        ]
      }
    },
    "Showcase 2.0": {
      "plain": "- red 1\n- red 2\n- green\n    - [@eckertThesisCEP]\n- yellow\n    - yellow property\n- dark blue\n    - [@eckertThesisCEP]\n    - more properties\n- grey\n- light blue\n",
      "childs": {
        "0": [
          [
            {
              "content": "red 1",
              "plain": "red 1\n",
              "plainChilds": "",
              "childs": []
            },
            {
              "content": "red 2",
              "plain": "red 2\n",
              "plainChilds": "",
              "childs": []
            },
            {
              "content": "green",
              "plain": "green\n",
              "plainChilds": "    - [@eckertThesisCEP]\n",
              "childs": [
                {
                  "content": ",[@eckertThesisCEP]",
                  "plain": "[@eckertThesisCEP]\n",
                  "plainChilds": "",
                  "childs": []
                }
              ]
            },
            {
              "content": "yellow",
              "plain": "yellow\n",
              "plainChilds": "    - yellow property\n",
              "childs": [
                {
                  "content": "yellow property",
                  "plain": "yellow property\n",
                  "plainChilds": "",
                  "childs": []
                }
              ]
            },
            {
              "content": "dark blue",
              "plain": "dark blue\n",
              "plainChilds": "    - [@eckertThesisCEP]\n    - more properties\n",
              "childs": [
                {
                  "content": ",[@eckertThesisCEP]",
                  "plain": "[@eckertThesisCEP]\n    ",
                  "plainChilds": "",
                  "childs": []
                },
                {
                  "content": "more properties",
                  "plain": "more properties\n",
                  "plainChilds": "",
                  "childs": []
                }
              ]
            },
            {
              "content": "grey",
              "plain": "grey\n",
              "plainChilds": "",
              "childs": []
            },
            {
              "content": "light blue",
              "plain": "light blue\n",
              "plainChilds": "",
              "childs": []
            }
          ]
        ]
      }
    },
    "Description": {
      "plain": "Default long description in __markdown__.\n- Bibkey example [@Adi:2004:ASM:988145.988150]\n- [Link example](http://example.com).",
      "childs": {
        "0": [
          "Default long description in __markdown__. - Bibkey example [@Adi:2004:ASM:988145.988150] - [Link example]."
        ]
      }
    },
    "Rating": {
      "plain": "- [5] Template is perfect\n- [1] I don't understand nothing\n- [3] It works\n",
      "childs": {
        "0": [
          [
            {
              "content": ",[5] Template is perfect",
              "plain": "[5] Template is perfect\n",
              "plainChilds": "",
              "childs": []
            },
            {
              "content": ",[1] I don't understand nothing",
              "plain": "[1] I don't understand nothing\n",
              "plainChilds": "",
              "childs": []
            },
            {
              "content": ",[3] It works",
              "plain": "[3] It works\n",
              "plainChilds": "",
              "childs": []
            }
          ]
        ]
      }
    },
    "Uncolored": {
      "plain": "- color 1\n",
      "childs": {
        "0": [
          [
            {
              "content": "color 1",
              "plain": "color 1\n",
              "plainChilds": "",
              "childs": []
            }
          ]
        ]
      }
    },
    "NumberColumn": {
      "plain": "- 200\u0000",
      "childs": {
        "0": [
          [
            {
              "content": "200",
              "plain": "200\u0000",
              "plainChilds": "",
              "childs": []
            }
          ]
        ]
      }
    }
  }
]